{
  "source": "amazon",
  "lastUpdated": "2025-09-21T07:07:47.881Z",
  "count": 3,
  "jobs": [
    {
      "title": "No title",
      "location": "No location",
      "jobId": "No Job ID",
      "datePosted": "No date",
      "url": "No URL",
      "source": "amazon",
      "company": "Amazon"
    },
    {
      "title": "No title",
      "location": "No location",
      "jobId": "No Job ID",
      "datePosted": "No date",
      "url": "No URL",
      "source": "amazon",
      "company": "Amazon"
    },
    {
      "title": "No title",
      "location": "No location",
      "jobId": "No Job ID",
      "datePosted": "No date",
      "url": "No URL",
      "source": "amazon",
      "company": "Amazon"
    }
  ]
}