{
  "source": "olx",
  "lastUpdated": "2025-12-29T03:53:37.613Z",
  "count": 56,
  "jobs": [
    {
      "title": "Kierowca Taxi Uber/Bolt Wrocław – Najlepsze Warunki, Nowe Samochody!",
      "company": "No company",
      "salary": "No salary",
      "salaryMin": null,
      "salaryMax": null,
      "salaryType": null,
      "location": "No location",
      "url": "https://www.olx.pl/oferta/praca/kierowca-taxi-uber-bolt-wroclaw-najlepsze-warunki-nowe-samochody-CID4-IDZFgws.html",
      "source": "olx"
    },
    {
      "title": "Płatny staż/praktyka - Marketing Assistant (Canva / Social Media)",
      "company": "No company",
      "salary": "No salary",
      "salaryMin": null,
      "salaryMax": null,
      "salaryType": null,
      "location": "No location",
      "url": "https://www.olx.pl/oferta/praca/platny-staz-praktyka-marketing-assistant-canva-social-media-CID4-ID18J9W1.html",
      "source": "olx"
    },
    {
      "title": "Stała praca od zaraz / biuro w centrum Wrocławia.",
      "company": "No company",
      "salary": "No salary",
      "salaryMin": null,
      "salaryMax": null,
      "salaryType": null,
      "location": "No location",
      "url": "https://www.olx.pl/oferta/praca/stala-praca-od-zaraz-biuro-w-centrum-wroclawia-CID4-ID18yUc4.html",
      "source": "olx"
    },
    {
      "title": "Heej! Szukasz pracy, która jest totalnym slay?",
      "company": "No company",
      "salary": "No salary",
      "salaryMin": null,
      "salaryMax": null,
      "salaryType": null,
      "location": "No location",
      "url": "https://www.olx.pl/oferta/praca/heej-szukasz-pracy-ktora-jest-totalnym-slay-CID4-ID18xgkN.html",
      "source": "olx"
    },
    {
      "title": "Staż w korporacji z j. angielskim - Helpdesk Analyst",
      "company": "No company",
      "salary": "No salary",
      "salaryMin": null,
      "salaryMax": null,
      "salaryType": null,
      "location": "No location",
      "url": "https://www.olx.pl/oferta/praca/staz-w-korporacji-z-j-angielskim-helpdesk-analyst-CID4-ID18Fo2E.html",
      "source": "olx"
    },
    {
      "title": "Praktyki i Staże w Taskscape Ltd – Informatyka, Cloud, AI",
      "company": "No company",
      "salary": "No salary",
      "salaryMin": null,
      "salaryMax": null,
      "salaryType": null,
      "location": "No location",
      "url": "https://www.olx.pl/oferta/praca/praktyki-i-staze-w-taskscape-ltd-informatyka-cloud-ai-CID4-ID18MOkn.html",
      "source": "olx"
    },
    {
      "title": "Kucharz kuchni polskiej (praktykant/junior) - Dubaj z zakwaterowaniem",
      "company": "No company",
      "salary": "No salary",
      "salaryMin": null,
      "salaryMax": null,
      "salaryType": null,
      "location": "No location",
      "url": "https://www.olx.pl/oferta/praca/kucharz-kuchni-polskiej-praktykant-junior-dubaj-z-zakwaterowaniem-CID4-ID18NZUW.html",
      "source": "olx"
    },
    {
      "title": "Дистанційна робота ,дроп-менеджер для Українців у Польщі. Підробіток",
      "company": "No company",
      "salary": "No salary",
      "salaryMin": null,
      "salaryMax": null,
      "salaryType": null,
      "location": "No location",
      "url": "https://www.olx.pl/oferta/praca/-CID4-ID180ID5.html",
      "source": "olx"
    },
    {
      "title": "Zrób za darmo kurs kwalifikowanego pracownika ochrony z bronią!",
      "company": "No company",
      "salary": "No salary",
      "salaryMin": null,
      "salaryMax": null,
      "salaryType": null,
      "location": "No location",
      "url": "https://www.olx.pl/oferta/praca/zrob-za-darmo-kurs-kwalifikowanego-pracownika-ochrony-z-bronia-CID4-ID181SL4.html",
      "source": "olx"
    },
    {
      "title": "Studio FIGURA Wrocław Złotniki - SPRZEDAŻ i modelowanie sylwetki",
      "company": "No company",
      "salary": "No salary",
      "salaryMin": null,
      "salaryMax": null,
      "salaryType": null,
      "location": "No location",
      "url": "https://www.olx.pl/oferta/praca/studio-figura-wroclaw-zlotniki-sprzedaz-i-modelowanie-sylwetki-CID4-ID18Hw5f.html",
      "source": "olx"
    },
    {
      "title": "4PL Planning Intern with English (m/w/x*)",
      "company": "No company",
      "salary": "No salary",
      "salaryMin": null,
      "salaryMax": null,
      "salaryType": null,
      "location": "No location",
      "url": "https://www.olx.pl/oferta/praca/4pl-planning-intern-with-english-m-w-x-CID4-ID18Cs1y.html",
      "source": "olx"
    },
    {
      "title": "Wiercenie i bruzdowanie - praca fizyczna",
      "company": "No company",
      "salary": "No salary",
      "salaryMin": null,
      "salaryMax": null,
      "salaryType": null,
      "location": "No location",
      "url": "https://www.olx.pl/oferta/praca/wiercenie-i-bruzdowanie-praca-fizyczna-CID4-ID168XN2.html",
      "source": "olx"
    },
    {
      "title": "praca na ręcznej myjni samochodowej",
      "company": "No company",
      "salary": "No salary",
      "salaryMin": null,
      "salaryMax": null,
      "salaryType": null,
      "location": "No location",
      "url": "https://www.olx.pl/oferta/praca/praca-na-recznej-myjni-samochodowej-CID4-IDOhHPt.html",
      "source": "olx"
    },
    {
      "title": "Firma transportowa zatrudni Spedytora/dyspozytora",
      "company": "No company",
      "salary": "No salary",
      "salaryMin": null,
      "salaryMax": null,
      "salaryType": null,
      "location": "No location",
      "url": "https://www.olx.pl/oferta/praca/firma-transportowa-zatrudni-spedytora-dyspozytora-CID4-ID18zADI.html",
      "source": "olx"
    },
    {
      "title": "Doradca klienta, sprzedawca",
      "company": "No company",
      "salary": "No salary",
      "salaryMin": null,
      "salaryMax": null,
      "salaryType": null,
      "location": "No location",
      "url": "https://www.olx.pl/oferta/praca/doradca-klienta-sprzedawca-CID4-ID18FnOH.html",
      "source": "olx"
    },
    {
      "title": "OGŁOSZENIE O PRACE - kierowca kat. B bus blaszak",
      "company": "No company",
      "salary": "No salary",
      "salaryMin": null,
      "salaryMax": null,
      "salaryType": null,
      "location": "No location",
      "url": "https://www.olx.pl/oferta/praca/ogloszenie-o-prace-kierowca-kat-b-bus-blaszak-CID4-ID17jtVw.html",
      "source": "olx"
    },
    {
      "title": "mechanik samochodowy",
      "company": "No company",
      "salary": "No salary",
      "salaryMin": null,
      "salaryMax": null,
      "salaryType": null,
      "location": "No location",
      "url": "https://www.olx.pl/oferta/praca/mechanik-samochodowy-CID4-ID18ybJR.html",
      "source": "olx"
    },
    {
      "title": "Nauczyciel/Nauczycielka do szkoły językowej Chat Easy English School",
      "company": "No company",
      "salary": "No salary",
      "salaryMin": null,
      "salaryMax": null,
      "salaryType": null,
      "location": "No location",
      "url": "https://www.olx.pl/oferta/praca/nauczyciel-nauczycielka-do-szkoly-jezykowej-chat-easy-english-school-CID4-ID17IS4w.html",
      "source": "olx"
    },
    {
      "title": "Młodsza księgowa / Młodszy księgowy",
      "company": "No company",
      "salary": "No salary",
      "salaryMin": null,
      "salaryMax": null,
      "salaryType": null,
      "location": "No location",
      "url": "https://www.olx.pl/oferta/praca/mlodsza-ksiegowa-mlodszy-ksiegowy-CID4-ID18Eb1r.html",
      "source": "olx"
    },
    {
      "title": "Praca dodatkowa jako trener w Superminds Academy pon, pt i soboty",
      "company": "No company",
      "salary": "No salary",
      "salaryMin": null,
      "salaryMax": null,
      "salaryType": null,
      "location": "No location",
      "url": "https://www.olx.pl/oferta/praca/praca-dodatkowa-jako-trener-w-superminds-academy-pon-pt-i-soboty-CID4-ID18Hfq0.html",
      "source": "olx"
    },
    {
      "title": "Poszukiwana Opiekunka Dziecięca _Żłobek Zakrzowskie Skrzaty",
      "company": "No company",
      "salary": "No salary",
      "salaryMin": null,
      "salaryMax": null,
      "salaryType": null,
      "location": "No location",
      "url": "https://www.olx.pl/oferta/praca/poszukiwana-opiekunka-dziecieca-zlobek-zakrzowskie-skrzaty-CID4-ID14aOwH.html",
      "source": "olx"
    },
    {
      "title": "Sprzedawca/Doradca klienta 25-35zł /na rękę",
      "company": "No company",
      "salary": "No salary",
      "salaryMin": null,
      "salaryMax": null,
      "salaryType": null,
      "location": "No location",
      "url": "https://www.olx.pl/oferta/praca/sprzedawca-doradca-klienta-25-35zl-na-reke-CID4-ID18BV0Z.html",
      "source": "olx"
    },
    {
      "title": "Pracownik myjni samochodowej",
      "company": "No company",
      "salary": "No salary",
      "salaryMin": null,
      "salaryMax": null,
      "salaryType": null,
      "location": "No location",
      "url": "https://www.olx.pl/oferta/praca/pracownik-myjni-samochodowej-CID4-ID187eNY.html",
      "source": "olx"
    },
    {
      "title": "Mechanik samochodowy / doradca klienta poszukiwany",
      "company": "No company",
      "salary": "No salary",
      "salaryMin": null,
      "salaryMax": null,
      "salaryType": null,
      "location": "No location",
      "url": "https://www.olx.pl/oferta/praca/mechanik-samochodowy-doradca-klienta-poszukiwany-CID4-ID18yhnx.html",
      "source": "olx"
    },
    {
      "title": "Zatrudnie do remontow mieszkan , gładzie płytki itp -",
      "company": "No company",
      "salary": "No salary",
      "salaryMin": null,
      "salaryMax": null,
      "salaryType": null,
      "location": "No location",
      "url": "https://www.olx.pl/oferta/praca/zatrudnie-do-remontow-mieszkan-gladzie-plytki-itp-CID4-ID18wbvE.html",
      "source": "olx"
    },
    {
      "title": "Poszukiwani pracownicy do prac remontowo-wykończeniowych",
      "company": "No company",
      "salary": "No salary",
      "salaryMin": null,
      "salaryMax": null,
      "salaryType": null,
      "location": "No location",
      "url": "https://www.olx.pl/oferta/praca/poszukiwani-pracownicy-do-prac-remontowo-wykonczeniowych-CID4-ID12fs5F.html",
      "source": "olx"
    },
    {
      "title": "MAGAZYNIER/KIEROWCA - praca w centrum Wrocławia!",
      "company": "No company",
      "salary": "No salary",
      "salaryMin": null,
      "salaryMax": null,
      "salaryType": null,
      "location": "No location",
      "url": "https://www.olx.pl/oferta/praca/magazynier-kierowca-praca-w-centrum-wroclawia-CID4-ID17Ex5B.html",
      "source": "olx"
    },
    {
      "title": "Młodszy Specjalista ds. Postępowań Egzekucyjnych",
      "company": "No company",
      "salary": "No salary",
      "salaryMin": null,
      "salaryMax": null,
      "salaryType": null,
      "location": "No location",
      "url": "https://www.olx.pl/oferta/praca/mlodszy-specjalista-ds-postepowan-egzekucyjnych-CID4-ID16WC2L.html",
      "source": "olx"
    },
    {
      "title": "Specjalista ds. sprzedaży telefonicznej",
      "company": "No company",
      "salary": "No salary",
      "salaryMin": null,
      "salaryMax": null,
      "salaryType": null,
      "location": "No location",
      "url": "https://www.olx.pl/oferta/praca/specjalista-ds-sprzedazy-telefonicznej-CID4-ID13bcO5.html",
      "source": "olx"
    },
    {
      "title": "Fizjoterapeuta poszukiwany",
      "company": "No company",
      "salary": "No salary",
      "salaryMin": null,
      "salaryMax": null,
      "salaryType": null,
      "location": "No location",
      "url": "https://www.olx.pl/oferta/praca/fizjoterapeuta-poszukiwany-CID4-IDPcAfq.html",
      "source": "olx"
    },
    {
      "title": "Kierowca Uber/Bolt - najlepsze warunki! Ty wybierasz dni pracy!",
      "company": "No company",
      "salary": "No salary",
      "salaryMin": null,
      "salaryMax": null,
      "salaryType": null,
      "location": "No location",
      "url": "https://www.olx.pl/oferta/praca/kierowca-uber-bolt-najlepsze-warunki-ty-wybierasz-dni-pracy-CID4-ID17nxf0.html",
      "source": "olx"
    },
    {
      "title": "Marketing – praktyka studencka (bezpłatna)",
      "company": "No company",
      "salary": "No salary",
      "salaryMin": null,
      "salaryMax": null,
      "salaryType": null,
      "location": "No location",
      "url": "https://www.olx.pl/oferta/praca/marketing-praktyka-studencka-bezplatna-CID4-ID16IBL4.html",
      "source": "olx"
    },
    {
      "title": "Asystent projektanta + inżynier budowy",
      "company": "No company",
      "salary": "No salary",
      "salaryMin": null,
      "salaryMax": null,
      "salaryType": null,
      "location": "No location",
      "url": "https://www.olx.pl/oferta/praca/asystent-projektanta-inzynier-budowy-CID4-ID18GAyW.html",
      "source": "olx"
    },
    {
      "title": "Barber Fryzjer poszukiwany poszukiwana",
      "company": "No company",
      "salary": "No salary",
      "salaryMin": null,
      "salaryMax": null,
      "salaryType": null,
      "location": "No location",
      "url": "https://www.olx.pl/oferta/praca/barber-fryzjer-poszukiwany-poszukiwana-CID4-ID184qkm.html",
      "source": "olx"
    },
    {
      "title": "Montaż systemów HVAC Klimatyzacja Wentylacja",
      "company": "No company",
      "salary": "No salary",
      "salaryMin": null,
      "salaryMax": null,
      "salaryType": null,
      "location": "No location",
      "url": "https://www.olx.pl/oferta/praca/montaz-systemow-hvac-klimatyzacja-wentylacja-CID4-ID17Kg82.html?reason=extended_search_extended_distance",
      "source": "olx"
    },
    {
      "title": "Magazynier – Praca od zaraz! Jedna zmiana, bez weekendów",
      "company": "No company",
      "salary": "No salary",
      "salaryMin": null,
      "salaryMax": null,
      "salaryType": null,
      "location": "No location",
      "url": "https://www.olx.pl/oferta/praca/magazynier-praca-od-zaraz-jedna-zmiana-bez-weekendow-CID4-ID15ZVxz.html?reason=extended_search_extended_distance",
      "source": "olx"
    },
    {
      "title": "Zatrudnimy mechanika maszyn rolniczych/pojazdów silnikowych",
      "company": "No company",
      "salary": "No salary",
      "salaryMin": null,
      "salaryMax": null,
      "salaryType": null,
      "location": "No location",
      "url": "https://www.olx.pl/oferta/praca/zatrudnimy-mechanika-maszyn-rolniczych-pojazdow-silnikowych-CID4-ID18xl85.html?reason=extended_search_extended_distance",
      "source": "olx"
    },
    {
      "title": "Technik / Inżynier Utrzymania Ruchu i Automatyzacji",
      "company": "No company",
      "salary": "No salary",
      "salaryMin": null,
      "salaryMax": null,
      "salaryType": null,
      "location": "No location",
      "url": "https://www.olx.pl/oferta/praca/technik-inzynier-utrzymania-ruchu-i-automatyzacji-CID4-ID18yTyZ.html?reason=extended_search_extended_distance",
      "source": "olx"
    },
    {
      "title": "Operator Maszyny CNC - Frezarka - Sterowanie Heidenhain 530",
      "company": "No company",
      "salary": "No salary",
      "salaryMin": null,
      "salaryMax": null,
      "salaryType": null,
      "location": "No location",
      "url": "https://www.olx.pl/oferta/praca/operator-maszyny-cnc-frezarka-sterowanie-heidenhain-530-CID4-ID17JLec.html?reason=extended_search_extended_distance",
      "source": "olx"
    },
    {
      "title": "Spedytor drobnicowy",
      "company": "No company",
      "salary": "No salary",
      "salaryMin": null,
      "salaryMax": null,
      "salaryType": null,
      "location": "No location",
      "url": "https://www.olx.pl/oferta/praca/spedytor-drobnicowy-CID4-ID188RYx.html?reason=extended_search_extended_distance",
      "source": "olx"
    },
    {
      "title": "Zatrudnienie pracownika do elewacji",
      "company": "No company",
      "salary": "No salary",
      "salaryMin": null,
      "salaryMax": null,
      "salaryType": null,
      "location": "No location",
      "url": "https://www.olx.pl/oferta/praca/zatrudnienie-pracownika-do-elewacji-CID4-ID15czbF.html?reason=extended_search_extended_distance",
      "source": "olx"
    },
    {
      "title": "Zatrudnimy barbera",
      "company": "No company",
      "salary": "No salary",
      "salaryMin": null,
      "salaryMax": null,
      "salaryType": null,
      "location": "No location",
      "url": "https://www.olx.pl/oferta/praca/zatrudnimy-barbera-CID4-ID17jqUq.html?reason=extended_search_extended_distance",
      "source": "olx"
    },
    {
      "title": "Stażysta / Stażystka ds. Marketingu",
      "company": "No company",
      "salary": "No salary",
      "salaryMin": null,
      "salaryMax": null,
      "salaryType": null,
      "location": "No location",
      "url": "https://www.olx.pl/oferta/praca/stazysta-stazystka-ds-marketingu-CID4-ID18yTe5.html?reason=extended_search_extended_distance",
      "source": "olx"
    },
    {
      "title": "Agent Ubezpieczeniowy, pracownik biurowy ubezpieczenia",
      "company": "No company",
      "salary": "No salary",
      "salaryMin": null,
      "salaryMax": null,
      "salaryType": null,
      "location": "No location",
      "url": "https://www.olx.pl/oferta/praca/agent-ubezpieczeniowy-pracownik-biurowy-ubezpieczenia-CID4-ID18CHPb.html?reason=extended_search_extended_distance",
      "source": "olx"
    },
    {
      "title": "Praca w agencji Social Media",
      "company": "No company",
      "salary": "No salary",
      "salaryMin": null,
      "salaryMax": null,
      "salaryType": null,
      "location": "No location",
      "url": "https://www.olx.pl/oferta/praca/praca-w-agencji-social-media-CID4-ID14Fikv.html?reason=extended_search_extended_distance",
      "source": "olx"
    },
    {
      "title": "Zatrudnie Asystentke Stomatologiczna",
      "company": "No company",
      "salary": "No salary",
      "salaryMin": null,
      "salaryMax": null,
      "salaryType": null,
      "location": "No location",
      "url": "https://www.olx.pl/oferta/praca/zatrudnie-asystentke-stomatologiczna-CID4-ID18lff1.html?reason=extended_search_extended_distance",
      "source": "olx"
    },
    {
      "title": "Referent ds. planowania",
      "company": "No company",
      "salary": "No salary",
      "salaryMin": null,
      "salaryMax": null,
      "salaryType": null,
      "location": "No location",
      "url": "https://www.olx.pl/oferta/praca/referent-ds-planowania-CID4-ID18Bkvr.html?reason=extended_search_extended_distance",
      "source": "olx"
    },
    {
      "title": "Barman/ Barmanka z doświadczeniem",
      "company": "No company",
      "salary": "No salary",
      "salaryMin": null,
      "salaryMax": null,
      "salaryType": null,
      "location": "No location",
      "url": "https://www.olx.pl/oferta/praca/barman-barmanka-z-doswiadczeniem-CID4-ID18LxBk.html?reason=extended_search_extended_distance",
      "source": "olx"
    },
    {
      "title": "Barman/ Barmanka",
      "company": "No company",
      "salary": "No salary",
      "salaryMin": null,
      "salaryMax": null,
      "salaryType": null,
      "location": "No location",
      "url": "https://www.olx.pl/oferta/praca/barman-barmanka-CID4-IDQSK38.html?reason=extended_search_extended_distance",
      "source": "olx"
    },
    {
      "title": "Muzyk - Wokalista - Pianista",
      "company": "No company",
      "salary": "No salary",
      "salaryMin": null,
      "salaryMax": null,
      "salaryType": null,
      "location": "No location",
      "url": "https://www.olx.pl/oferta/praca/muzyk-wokalista-pianista-CID4-ID184GIP.html?reason=extended_search_extended_distance",
      "source": "olx"
    },
    {
      "title": "Psychoterapeuta,Psycholog,Psychodietetyk,Seksuolog",
      "company": "No company",
      "salary": "No salary",
      "salaryMin": null,
      "salaryMax": null,
      "salaryType": null,
      "location": "No location",
      "url": "https://www.olx.pl/oferta/praca/psychoterapeuta-psycholog-psychodietetyk-seksuolog-CID4-ID13JccU.html?reason=extended_search_extended_distance",
      "source": "olx"
    },
    {
      "title": "Kierowca C - Iveco 7,2t. 15 ep. szkolenie. Panie mile widziane",
      "company": "No company",
      "salary": "No salary",
      "salaryMin": null,
      "salaryMax": null,
      "salaryType": null,
      "location": "No location",
      "url": "https://www.olx.pl/oferta/praca/kierowca-c-iveco-7-2t-15-ep-szkolenie-panie-mile-widziane-CID4-ID18xIr6.html?reason=extended_search_extended_distance",
      "source": "olx"
    },
    {
      "title": "Szukamy pracowników budowlanych",
      "company": "No company",
      "salary": "No salary",
      "salaryMin": null,
      "salaryMax": null,
      "salaryType": null,
      "location": "No location",
      "url": "https://www.olx.pl/oferta/praca/szukamy-pracownikow-budowlanych-CID4-ID18LTCU.html?reason=extended_search_extended_distance",
      "source": "olx"
    },
    {
      "title": "Doradca klienta OPTYK",
      "company": "No company",
      "salary": "No salary",
      "salaryMin": null,
      "salaryMax": null,
      "salaryType": null,
      "location": "No location",
      "url": "https://www.olx.pl/oferta/praca/doradca-klienta-optyk-CID4-ID18OLqa.html?reason=extended_search_extended_distance",
      "source": "olx"
    },
    {
      "title": "Wykończenia wnętrz",
      "company": "No company",
      "salary": "No salary",
      "salaryMin": null,
      "salaryMax": null,
      "salaryType": null,
      "location": "No location",
      "url": "https://www.olx.pl/oferta/praca/wykonczenia-wnetrz-CID4-ID18JZnA.html?reason=extended_search_extended_distance",
      "source": "olx"
    },
    {
      "title": "Pracownik restauracji",
      "company": "No company",
      "salary": "No salary",
      "salaryMin": null,
      "salaryMax": null,
      "salaryType": null,
      "location": "No location",
      "url": "https://www.olx.pl/oferta/praca/pracownik-restauracji-CID4-ID18DFFM.html?reason=extended_search_extended_distance",
      "source": "olx"
    }
  ]
}